shakecastaebm/__init__.py
shakecastaebm/capacity.py
shakecastaebm/core.py
shakecastaebm/damage.py
shakecastaebm/damping.py
shakecastaebm/data_tables.py
shakecastaebm/demand.py
shakecastaebm/performance_point.py
shakecastaebm/sanaz.py
shakecastaebm/spectrum.py
shakecastaebm/tests/__init__.py
shakecastaebm/tests/bundle.py
shakecastaebm/tests/core.py
shakecastaebm/tests/damage.py
shakecastaebm/tests/damping.py
shakecastaebm/tests/performance_point.py
shakecastaebm/tests/spectrum.py
shakecastaebm/validation/__init__.py
shakecastaebm/validation/bundle.py
shakecastaebm/validation/damping.py
shakecastaebm/validation/data.py
shakecastaebm/validation/demand.py
shakecastaebm/validation/generate.py
shakecastaebm/validation/shakecast.py
shakecastaebm/validation/workbook.py
shakecast_aebm-1.0.0.dist-info/LICENSE.md
shakecast_aebm-1.0.0.dist-info/METADATA
shakecast_aebm-1.0.0.dist-info/WHEEL
shakecast_aebm-1.0.0.dist-info/top_level.txt
shakecast_aebm-1.0.0.dist-info/RECORD
